{"data":{"referenced_tweets":[{"type":"replied_to","id":"1310358914991489024"}],"in_reply_to_user_id":"904740870817120256","text":"\uD83D\uDEA8Evacuation Order #NapaCounty #GlassFire 4:32pm\nEastside Silverado Trail from Howell Mountain south to Taplin Road including all of Taplin Road and the entirety of roads in between.\nhttps://t.co/IXNpd7dixa","id":"1310365746761883648","entities":{"annotations":[{"start":19,"end":28,"probability":0.3283,"type":"Place","normalized_text":"NapaCounty"},{"start":48,"end":71,"probability":0.5274,"type":"Other","normalized_text":"Eastside Silverado Trail"},{"start":78,"end":92,"probability":0.7772,"type":"Place","normalized_text":"Howell Mountain"},{"start":103,"end":113,"probability":0.5457,"type":"Place","normalized_text":"Taplin Road"},{"start":132,"end":142,"probability":0.4801,"type":"Place","normalized_text":"Taplin Road"}],"urls":[{"start":182,"end":205,"url":"https://t.co/IXNpd7dixa","expanded_url":"https://local.nixle.com/alert/8267844/","display_url":"local.nixle.com/alert/8267844/","status":200,"unwound_url":"https://local.nixle.com/alert/8267844/"}],"hashtags":[{"start":18,"end":29,"tag":"NapaCounty"},{"start":30,"end":40,"tag":"GlassFire"}]},"edit_history_tweet_ids":["1310365746761883648"],"created_at":"2020-09-27T23:48:34.000Z","conversation_id":"1310192413542154242","author_id":"904740870817120256"},"includes":{"users":[{"id":"904740870817120256","name":"CEDR Digital Corps","username":"CEDRdigital"}],"tweets":[{"referenced_tweets":[{"type":"replied_to","id":"1310358913326305281"}],"in_reply_to_user_id":"904740870817120256","text":"\uD83D\uDEA8Evacuaciones obligatorias del condado de #Napa 4:09pm\neste de Silverado Trail desde la calle Deer Park Road hasta Meadowood Road, incluyendo todas las carreteras al lado este entre estas calles. Esto incluye el Meadowood Resort.\n#GlassFire\nhttps://t.co/YomJwf98zy","id":"1310358914991489024","entities":{"annotations":[{"start":43,"end":46,"probability":0.4521,"type":"Place","normalized_text":"Napa"},{"start":63,"end":77,"probability":0.6456,"type":"Other","normalized_text":"Silverado Trail"},{"start":94,"end":107,"probability":0.6153,"type":"Place","normalized_text":"Deer Park Road"},{"start":115,"end":128,"probability":0.7779,"type":"Place","normalized_text":"Meadowood Road"},{"start":212,"end":227,"probability":0.5566,"type":"Place","normalized_text":"Meadowood Resort"},{"start":231,"end":239,"probability":0.5274,"type":"Other","normalized_text":"GlassFire"}],"urls":[{"start":241,"end":264,"url":"https://t.co/YomJwf98zy","expanded_url":"https://local.nixle.com/alert/8267822/?l=es","display_url":"local.nixle.com/alert/8267822/…","status":200,"unwound_url":"https://local.nixle.com/alert/8267822/?l=es"}],"hashtags":[{"start":42,"end":47,"tag":"Napa"},{"start":230,"end":240,"tag":"GlassFire"}]},"edit_history_tweet_ids":["1310358914991489024"],"created_at":"2020-09-27T23:21:25.000Z","conversation_id":"1310192413542154242","author_id":"904740870817120256"}]}}