{"data":{"author_id":"2183520866","edit_history_tweet_ids":["1005637230575026176"],"in_reply_to_user_id":"2183520866","text":"#ChromeFire\n40=&gt;500=&gt;700 acres\n0% =&gt;10% containment\nN of ElkCreek #GlennCounty\nMandatory #Evacuations/Road Closures In Effect\n#YubaNet INFO=&gt;https://t.co/NOq4dtxLRZ \n#NorCal #NorCalFire #CAFire #CALFire","id":"1005637230575026176","entities":{"annotations":[{"start":1,"end":10,"probability":0.8709,"type":"Other","normalized_text":"ChromeFire"},{"start":66,"end":73,"probability":0.4258,"type":"Other","normalized_text":"ElkCreek"},{"start":76,"end":86,"probability":0.414,"type":"Other","normalized_text":"GlennCounty"},{"start":136,"end":142,"probability":0.4707,"type":"Other","normalized_text":"YubaNet"}],"urls":[{"start":153,"end":176,"url":"https://t.co/NOq4dtxLRZ","expanded_url":"https://yubanet.com/Fires/chrome/","display_url":"yubanet.com/Fires/chrome/","status":200,"unwound_url":"http://yubanet.com/containedca16/chrome/"}],"hashtags":[{"start":0,"end":11,"tag":"ChromeFire"},{"start":75,"end":87,"tag":"GlennCounty"},{"start":98,"end":110,"tag":"Evacuations"},{"start":135,"end":143,"tag":"YubaNet"},{"start":178,"end":185,"tag":"NorCal"},{"start":186,"end":197,"tag":"NorCalFire"},{"start":198,"end":205,"tag":"CAFire"},{"start":206,"end":214,"tag":"CALFire"}]},"referenced_tweets":[{"type":"replied_to","id":"1005623714237411328"}],"conversation_id":"1005612463897784320","created_at":"2018-06-10T02:26:14.000Z"},"includes":{"users":[{"id":"2183520866","name":"tiniskwerl","username":"tiniskwerl"}],"tweets":[{"author_id":"2183520866","edit_history_tweet_ids":["1005623714237411328"],"in_reply_to_user_id":"2183520866","text":"#ChromeFire\n40=&gt;500 acres/0% perimeter containment\nN of ElkCreek #GlennCounty\nMandatory #Evacuations/Road Closures In Effect\n#LiveUpdates #YubaNet=&gt;https://t.co/NOq4dtxLRZ\n#NorCal #NorCalFire #CAFire #CALFire","id":"1005623714237411328","entities":{"annotations":[{"start":1,"end":10,"probability":0.8396,"type":"Other","normalized_text":"ChromeFire"},{"start":59,"end":66,"probability":0.4563,"type":"Other","normalized_text":"ElkCreek"},{"start":69,"end":79,"probability":0.4332,"type":"Other","normalized_text":"GlennCounty"},{"start":142,"end":148,"probability":0.5288,"type":"Other","normalized_text":"YubaNet"}],"urls":[{"start":154,"end":177,"url":"https://t.co/NOq4dtxLRZ","expanded_url":"https://yubanet.com/Fires/chrome/","display_url":"yubanet.com/Fires/chrome/","status":200,"unwound_url":"http://yubanet.com/containedca16/chrome/"}],"hashtags":[{"start":0,"end":11,"tag":"ChromeFire"},{"start":68,"end":80,"tag":"GlennCounty"},{"start":91,"end":103,"tag":"Evacuations"},{"start":128,"end":140,"tag":"LiveUpdates"},{"start":141,"end":149,"tag":"YubaNet"},{"start":178,"end":185,"tag":"NorCal"},{"start":186,"end":197,"tag":"NorCalFire"},{"start":198,"end":205,"tag":"CAFire"},{"start":206,"end":214,"tag":"CALFire"}]},"referenced_tweets":[{"type":"replied_to","id":"1005612463897784320"}],"conversation_id":"1005612463897784320","created_at":"2018-06-10T01:32:31.000Z"}]}}